{
  "parent": "minecraft:recipes/root",
  "rewards": {
    "recipes": [
      "treasure2:spider_key"
    ]
  },
  "criteria": {
    "has_the_recipe": {
      "trigger": "minecraft:recipe_unlocked",
      "conditions": {
        "recipe": "treasure2:spider_key"
      }
    },
    "has_iron_key": {
      "trigger": "minecraft:inventory_changed",
      "conditions": {
        "items": [
          {
            "item": "treasure2:iron_key"
          }
        ]
      }
    }
  },
  "requirements": [
    [
      "has_the_recipe",
      "has_iron_key"
    ]
  ]
}